madtypes/__init__.py
madtypes-0.0.9.dist-info/LICENSE
madtypes-0.0.9.dist-info/METADATA
madtypes-0.0.9.dist-info/WHEEL
madtypes-0.0.9.dist-info/top_level.txt
madtypes-0.0.9.dist-info/RECORD
