Metadata-Version: 2.1
Name: madtypes
Version: 0.0.9
Summary: Python typing that raise TypeError at runtime
Home-page: https://github.com/6r17/madtypes
Author: 6r17
Author-email: patrick.borowy@proton.me
Keywords: typing,json,json-schema
Classifier: Intended Audience :: Developers
Classifier: License :: OSI Approved :: MIT License
Classifier: Programming Language :: Python
Classifier: Programming Language :: Python :: 3
Requires-Python: >=3.10
License-File: LICENSE
